humulus/__init__.py
humulus/_version.py
humulus/app.py
humulus/auth.py
humulus/couch.py
humulus/filters.py
humulus/home.py
humulus/recipes.py
humulus/styles.py
humulus/designs/recipes.json
humulus/designs/styles.json
humulus/static/favicon.ico
humulus/static/moment.min.js
humulus/static/recipes.js
humulus/static/style.css
humulus/templates/_base.html
humulus/templates/_error.html
humulus/templates/_macros.html
humulus/templates/about.html
humulus/templates/index.html
humulus/templates/auth/login.html
humulus/templates/recipes/_macros.html
humulus/templates/recipes/create.html
humulus/templates/recipes/create_json.html
humulus/templates/recipes/index.html
humulus/templates/recipes/info.html
humulus/templates/recipes/update.html
humulus/templates/styles/index.html
humulus/templates/styles/info.html
humulus/templates/styles/recipes.html
humulus-0.1.0.dist-info/LICENSE
humulus-0.1.0.dist-info/METADATA
humulus-0.1.0.dist-info/WHEEL
humulus-0.1.0.dist-info/top_level.txt
humulus-0.1.0.dist-info/RECORD
