Metadata-Version: 2.1
Name: humulus
Version: 0.1.0
Summary: Humulus is a beer recipe builder.
Home-page: https://github.com/shouptech/humulus
Author: Mike Shoup
Author-email: mike@shoup.io
License: UNKNOWN
Platform: UNKNOWN
Classifier: Development Status :: 5 - Production/Stable
Classifier: Environment :: Web Environment
Classifier: Framework :: Flask
Classifier: License :: OSI Approved :: Apache Software License
Classifier: Operating System :: OS Independent
Classifier: Programming Language :: Python :: 3
Classifier: Topic :: Internet :: WWW/HTTP :: WSGI :: Application
Requires-Dist: Flask (==1.0.3)
Requires-Dist: Flask-WTF (==0.14.2)
Requires-Dist: simplejson (==3.16.0)
Requires-Dist: python-slugify (==3.0.2)
Requires-Dist: cloudant (==2.12.0)
